surface_tracker/__init__.py
surface_tracker/camera.py
surface_tracker/coordinate_space.py
surface_tracker/corner.py
surface_tracker/heatmap.py
surface_tracker/image_crop.py
surface_tracker/location.py
surface_tracker/marker.py
surface_tracker/orientation.py
surface_tracker/surface.py
surface_tracker/tracker.py
surface_tracker/utils.py
surface_tracker/visual_anchors.py
surface_tracker-0.0.1.dist-info/LICENSE
surface_tracker-0.0.1.dist-info/METADATA
surface_tracker-0.0.1.dist-info/WHEEL
surface_tracker-0.0.1.dist-info/top_level.txt
surface_tracker-0.0.1.dist-info/RECORD
